{
    "MRData": {
        "xmlns": "http://ergast.com/mrd/1.4",
        "series": "f1",
        "url": "http://ergast.com/api/f1/constructors/fittipaldi/constructorstandings.json",
        "limit": "30",
        "offset": "0",
        "total": "8",
        "StandingsTable": {
            "constructorId": "fittipaldi",
            "StandingsLists": [
                {
                    "season": "1975",
                    "round": "14",
                    "ConstructorStandings": [
                        {
                            "position": "16",
                            "positionText": "16",
                            "points": "0",
                            "wins": "0",
                            "Constructor": {
                                "constructorId": "fittipaldi",
                                "url": "http://en.wikipedia.org/wiki/Fittipaldi_%28constructor%29",
                                "name": "Fittipaldi",
                                "nationality": "Brazilian"
                            }
                        }
                    ]
                },
                {
                    "season": "1976",
                    "round": "16",
                    "ConstructorStandings": [
                        {
                            "position": "11",
                            "positionText": "11",
                            "points": "3",
                            "wins": "0",
                            "Constructor": {
                                "constructorId": "fittipaldi",
                                "url": "http://en.wikipedia.org/wiki/Fittipaldi_%28constructor%29",
                                "name": "Fittipaldi",
                                "nationality": "Brazilian"
                            }
                        }
                    ]
                },
                {
                    "season": "1977",
                    "round": "17",
                    "ConstructorStandings": [
                        {
                            "position": "9",
                            "positionText": "9",
                            "points": "11",
                            "wins": "0",
                            "Constructor": {
                                "constructorId": "fittipaldi",
                                "url": "http://en.wikipedia.org/wiki/Fittipaldi_%28constructor%29",
                                "name": "Fittipaldi",
                                "nationality": "Brazilian"
                            }
                        }
                    ]
                },
                {
                    "season": "1978",
                    "round": "16",
                    "ConstructorStandings": [
                        {
                            "position": "7",
                            "positionText": "7",
                            "points": "17",
                            "wins": "0",
                            "Constructor": {
                                "constructorId": "fittipaldi",
                                "url": "http://en.wikipedia.org/wiki/Fittipaldi_%28constructor%29",
                                "name": "Fittipaldi",
                                "nationality": "Brazilian"
                            }
                        }
                    ]
                },
                {
                    "season": "1979",
                    "round": "15",
                    "ConstructorStandings": [
                        {
                            "position": "12",
                            "positionText": "12",
                            "points": "1",
                            "wins": "0",
                            "Constructor": {
                                "constructorId": "fittipaldi",
                                "url": "http://en.wikipedia.org/wiki/Fittipaldi_%28constructor%29",
                                "name": "Fittipaldi",
                                "nationality": "Brazilian"
                            }
                        }
                    ]
                },
                {
                    "season": "1980",
                    "round": "14",
                    "ConstructorStandings": [
                        {
                            "position": "8",
                            "positionText": "8",
                            "points": "11",
                            "wins": "0",
                            "Constructor": {
                                "constructorId": "fittipaldi",
                                "url": "http://en.wikipedia.org/wiki/Fittipaldi_%28constructor%29",
                                "name": "Fittipaldi",
                                "nationality": "Brazilian"
                            }
                        }
                    ]
                },
                {
                    "season": "1981",
                    "round": "15",
                    "ConstructorStandings": [
                        {
                            "position": "15",
                            "positionText": "15",
                            "points": "0",
                            "wins": "0",
                            "Constructor": {
                                "constructorId": "fittipaldi",
                                "url": "http://en.wikipedia.org/wiki/Fittipaldi_%28constructor%29",
                                "name": "Fittipaldi",
                                "nationality": "Brazilian"
                            }
                        }
                    ]
                },
                {
                    "season": "1982",
                    "round": "16",
                    "ConstructorStandings": [
                        {
                            "position": "13",
                            "positionText": "13",
                            "points": "1",
                            "wins": "0",
                            "Constructor": {
                                "constructorId": "fittipaldi",
                                "url": "http://en.wikipedia.org/wiki/Fittipaldi_%28constructor%29",
                                "name": "Fittipaldi",
                                "nationality": "Brazilian"
                            }
                        }
                    ]
                }
            ]
        }
    }
}