{
    "MRData": {
        "xmlns": "http://ergast.com/mrd/1.4",
        "series": "f1",
        "url": "http://ergast.com/api/f1/drivers/klodwig.json",
        "limit": "30",
        "offset": "0",
        "total": "1",
        "DriverTable": {
            "driverId": "klodwig",
            "Drivers": [
                {
                    "driverId": "klodwig",
                    "url": "http://en.wikipedia.org/wiki/Ernst_Klodwig",
                    "givenName": "Ernst",
                    "familyName": "Klodwig",
                    "dateOfBirth": "1903-05-23",
                    "nationality": "East German"
                }
            ]
        }
    }
}