{
    "MRData": {
        "xmlns": "http://ergast.com/mrd/1.4",
        "series": "f1",
        "url": "http://ergast.com/api/f1/drivers/mansell.json",
        "limit": "30",
        "offset": "0",
        "total": "1",
        "DriverTable": {
            "driverId": "mansell",
            "Drivers": [
                {
                    "driverId": "mansell",
                    "url": "http://en.wikipedia.org/wiki/Nigel_Mansell",
                    "givenName": "Nigel",
                    "familyName": "Mansell",
                    "dateOfBirth": "1953-08-08",
                    "nationality": "British"
                }
            ]
        }
    }
}