{
    "MRData": {
        "xmlns": "http://ergast.com/mrd/1.4",
        "series": "f1",
        "url": "http://ergast.com/api/f1/drivers/tambay.json",
        "limit": "30",
        "offset": "0",
        "total": "1",
        "DriverTable": {
            "driverId": "tambay",
            "Drivers": [
                {
                    "driverId": "tambay",
                    "url": "http://en.wikipedia.org/wiki/Patrick_Tambay",
                    "givenName": "Patrick",
                    "familyName": "Tambay",
                    "dateOfBirth": "1949-06-25",
                    "nationality": "French"
                }
            ]
        }
    }
}